sviewgui/__init__.py
sviewgui/sgui.py
sviewgui/sview.py
sviewgui-1.1.2.dist-info/METADATA
sviewgui-1.1.2.dist-info/WHEEL
sviewgui-1.1.2.dist-info/entry_points.txt
sviewgui-1.1.2.dist-info/top_level.txt
sviewgui-1.1.2.dist-info/RECORD
