Metadata-Version: 2.1
Name: sviewgui
Version: 1.1.2
Summary: Package Dependency: Validates package requirements
Home-page: https://github.com/SojiroFukuda/sview-gui
Author: SojiroFukuda
Author-email: S.Fukuda-2018@hull.ac.uk
Maintainer: SojiroFukuda
Maintainer-email: S.Fukuda-2018@hull.ac.uk
License: SojiroFukuda
Platform: UNKNOWN
Classifier: Programming Language :: Python :: 3
Classifier: Programming Language :: Python :: 3.3
Classifier: Programming Language :: Python :: 3.4
Classifier: Framework :: Matplotlib
Requires-Dist: Pathlib2 (>=2.3.0)
Requires-Dist: PyQt5 (>=5.7.0)
Requires-Dist: cmocean (>=2.0)
Requires-Dist: matplotlib (>=3.0.0)
Requires-Dist: numpy (>=1.16.0)
Requires-Dist: pandas (>=0.24.0)
Requires-Dist: pygments (>=2.4.0)
Requires-Dist: scipy (>=1.2.0)
Requires-Dist: seaborn (>=0.9.0)
